{
    "aArJ": {
        "first": "Joanna",
        "last": "Artwińska"
    },
    "aAsM": {
        "first": "Małgorzata",
        "last": "Aszendorf"
    },
    "qBiM": {
        "first": "Marta",
        "last": "Bielak-Bodnar"
    },
    "rBuB": {
        "first": "Bożena",
        "last": "Budkiewicz"
    },
    "hBuC": {
        "first": "Celina",
        "last": "Bujalska"
    },
    "aBuM": {
        "first": "Marta",
        "last": "Burzyńska"
    },
    "bBuD": {
        "first": "Danuta",
        "last": "Bussler"
    },
    "iBuK": {
        "first": "Konrad",
        "last": "Buzak"
    },
    "xChB": {
        "first": "Bożena",
        "last": "Chmielińska"
    },
    "mCzaG": {
        "first": "Grażyna",
        "last": "Czarnecka"
    },
    "aCzA": {
        "first": "Anna",
        "last": "Czarnowska"
    },
    "aCpA": {
        "first": "Agnieszka",
        "last": "Czepulonis"
    },
    "hCzeA": {
        "first": "Anna",
        "last": "Czernihowska-Tymoszyk"
    },
    "aĆwT": {
        "first": "Teresa",
        "last": "Ćwiklak"
    },
    "xDuA": {
        "first": "Anna",
        "last": "Duszak"
    },
    "\u0026DźD": {
        "first": "Dorota",
        "last": "Dźwig"
    },
    "gFabA": {
        "first": "Anita",
        "last": "Fabrycka"
    },
    "aFiR": {
        "first": "Renata",
        "last": "Fiałkowska"
    },
    "mFiJ": {
        "first": "Janina",
        "last": "Filipowicz"
    },
    "nGmA": {
        "first": "Adam",
        "last": "Gmyrek"
    },
    "sGóJ": {
        "first": "Jacek",
        "last": "Górski"
    },
    "sHeG": {
        "first": "Grzegorz",
        "last": "Henicz"
    },
    "gHleO": {
        "first": "Olga",
        "last": "Hlebko"
    },
    "gHłK": {
        "first": "Karolina",
        "last": "Hłasko"
    },
    "nHoJ": {
        "first": "Justyna",
        "last": "Horodecka-Nowicka"
    },
    "mIlM": {
        "first": "Małgorzata",
        "last": "Ilewicz"
    },
    "gIwH": {
        "first": "Hanna",
        "last": "Iwańska"
    },
    "\u0026JaJ": {
        "first": "Joanna",
        "last": "Jankowska"
    },
    "iJaB": {
        "first": "Bożena",
        "last": "Jaśkiewicz"
    },
    "mKieA": {
        "first": "Anna",
        "last": "Kierznikowicz"
    },
    "fKoA": {
        "first": "Artur",
        "last": "Kolincio"
    },
    "gKsW": {
        "first": "Wiesław",
        "last": "Kosakowski"
    },
    "tKoM": {
        "first": "Michał",
        "last": "Koss"
    },
    "gKoI": {
        "first": "Iwona",
        "last": "Kotowska"
    },
    "fKoE": {
        "first": "Elżbieta",
        "last": "Koziróg"
    },
    "aKrZ": {
        "first": "Zofia",
        "last": "Krakowiak-Michlewicz"
    },
    "YKrzA": {
        "first": "Alicja",
        "last": "Krzemieniewska"
    },
    "gKuM": {
        "first": "Małgorzata",
        "last": "Kubik"
    },
    "cKulI": {
        "first": "Irmina",
        "last": "Kulik"
    },
    "bKupM": {
        "first": "Małgorzata",
        "last": "Kupczyk-Skodowska"
    },
    "cKwE": {
        "first": "Elżbieta",
        "last": "Kwella"
    },
    "mLeJ": {
        "first": "Jacek",
        "last": "Lech"
    },
    "pLotM": {
        "first": "Magdalena",
        "last": "Lotterhoff"
    },
    "pŁaI": {
        "first": "Iwona",
        "last": "Łapińska"
    },
    "tŁoM": {
        "first": "Maria",
        "last": "Łojek-Kurzętkowska"
    },
    "sŁoK": {
        "first": "Katarzyna",
        "last": "Łończuk"
    },
    "hHoM": {
        "first": "Magdalena",
        "last": "Łozowicka-Honkisz"
    },
    "mŁuK": {
        "first": "Katarzyna",
        "last": "Łuczyńska"
    },
    "pMaB": {
        "first": "Brygida",
        "last": "Maciejewska"
    },
    "fMąM": {
        "first": "Marta",
        "last": "Mąkosa"
    },
    "qMelI": {
        "first": "Inesa",
        "last": "Melnychenko"
    },
    "pMeM": {
        "first": "Małgorzata",
        "last": "Meronk"
    },
    "pNiE": {
        "first": "Ewa",
        "last": "Niwińska-Lipińska"
    },
    "bNowA": {
        "first": "Alicja",
        "last": "Nowak"
    },
    "aNoJ": {
        "first": "Joanna",
        "last": "Nowak"
    },
    "sOgA": {
        "first": "Aleksandra",
        "last": "Ogiegło"
    },
    "bOleA": {
        "first": "Agnieszka",
        "last": "Olejniczak"
    },
    "tOlM": {
        "first": "Małgorzata",
        "last": "Olszowa"
    },
    "sOrłB": {
        "first": "Bożena",
        "last": "Orłowska"
    },
    "mOrA": {
        "first": "Agnieszka",
        "last": "Orzeszek"
    },
    "nPaB": {
        "first": "Brygida",
        "last": "Pacuła"
    },
    "mPaA": {
        "first": "Anita",
        "last": "Pawłowska"
    },
    "hPiD": {
        "first": "Dariusz",
        "last": "Piasek"
    },
    "pPieJ": {
        "first": "Joanna",
        "last": "Piechowiak"
    },
    "\u0026PieD": {
        "first": "Damian",
        "last": "Pietrowski"
    },
    "nPrU": {
        "first": "Urszula",
        "last": "Praska"
    },
    "pPrE": {
        "first": "Ewa",
        "last": "Prylińska"
    },
    "aPrA": {
        "first": "Aleksandra",
        "last": "Przekowiak"
    },
    "fPrzE": {
        "first": "Emilia",
        "last": "Przybysz"
    },
    "bRadK": {
        "first": "Katarzyna",
        "last": "Radzikowska"
    },
    "cRaJ": {
        "first": "Justyna",
        "last": "Raulin"
    },
    "aRoM": {
        "first": "Magdalena",
        "last": "Roda"
    },
    "xRozJ": {
        "first": "Joanna",
        "last": "Rozkwitalska"
    },
    "pRyJ": {
        "first": "Joanna",
        "last": "Rybicka"
    },
    "XRzA": {
        "first": "Anna",
        "last": "Rzepa"
    },
    "cSaD": {
        "first": "Danuta",
        "last": "Sadaj"
    },
    "mSklA": {
        "first": "Agnieszka",
        "last": "Skalska"
    },
    "aSmM": {
        "first": "Marta",
        "last": "Smalara-Lewandowska"
    },
    "YSteD": {
        "first": "Dorota",
        "last": "Stepaniuk"
    },
    "fSuW": {
        "first": "Włodzimierz",
        "last": "Subczyński"
    },
    "gSzcM": {
        "first": "Michał",
        "last": "Szczyptański"
    },
    "iSzR": {
        "first": "Ryszard",
        "last": "Szubartowski"
    },
    "sSzM": {
        "first": "Małgorzata",
        "last": "Szymańska-Pancewicz"
    },
    "iŚmJ": {
        "first": "Joanna",
        "last": "Śmierzchalska"
    },
    "cSwD": {
        "first": "Daria",
        "last": "Świderska"
    },
    "mTaS": {
        "first": "Sylwia",
        "last": "Tarała"
    },
    "nTaA": {
        "first": "Agata",
        "last": "Taźbierska"
    },
    "#TeoB": {
        "first": "Bożena",
        "last": "Teofilewska"
    },
    "mToW": {
        "first": "Wojciech",
        "last": "Tomalczyk"
    },
    "qTrA": {
        "first": "Anna",
        "last": "Trelińska"
    },
    "sUrG": {
        "first": "Grzegorz",
        "last": "Urgacz"
    },
    "hWaI": {
        "first": "Iwona",
        "last": "Walendziak"
    },
    "aWMiS": {
        "first": "Sława",
        "last": "Winiarska-Mielniczuk"
    },
    "(WnD": {
        "first": "Dorota",
        "last": "Wnuczyńska"
    },
    "aWoA": {
        "first": "Andrzej",
        "last": "Wojniusz"
    },
    "fWrO": {
        "first": "Olga",
        "last": "Wrońska"
    },
    "mZaW": {
        "first": "Witold",
        "last": "Zakrzacki"
    }
}